urlcheck/__init__.py
urlcheck-0.0.1.data/scripts/urlcheck
urlcheck-0.0.1.dist-info/METADATA
urlcheck-0.0.1.dist-info/WHEEL
urlcheck-0.0.1.dist-info/top_level.txt
urlcheck-0.0.1.dist-info/RECORD
