Metadata-Version: 2.1
Name: urlcheck
Version: 0.0.1
Summary: Python package for http health check
Home-page: UNKNOWN
Author: Park Joo-hyeon
Author-email: www.jrr.kr@gmail.com
License: UNKNOWN
Keywords: timerange
Platform: UNKNOWN
Classifier: Programming Language :: Python :: 3
Classifier: Programming Language :: Python :: 3.2
Classifier: Programming Language :: Python :: 3.3
Classifier: Programming Language :: Python :: 3.4
Classifier: Programming Language :: Python :: 3.5
Classifier: Programming Language :: Python :: 3.6
Classifier: Programming Language :: Python :: 3.8
Requires-Python: >=3
